[
  {
    "title": "Plants Vs Zombies_L5",
    "link_thumb": "https://live.staticflickr.com/65535/51686172018_4e1c44bc6b_o.gif",
    "id_album": "-1426777466",
    "total": 24,
    "size_max_detail_page": 1,
    "list_detail": [
      {
        "index_page": 0,
        "link_page": "https://github.com/lmbstudiocontact/mb4_dt_alb_0/raw/main/14132021_dta_-1426777466_index_0.json"
      }
    ]
  },
  {
    "title": "Animal Art_L10",
    "link_thumb": "https://live.staticflickr.com/65535/51673527134_a9ca8a0059_o.gif",
    "id_album": "-1287735957",
    "total": 7,
    "size_max_detail_page": 1,
    "list_detail": [
      {
        "index_page": 0,
        "link_page": "https://github.com/lmbstudiocontact/mb4_dt_alb_0/raw/main/14132021_dta_-1287735957_index_0.json"
      }
    ]
  },
  {
    "title": "Onmyoji_L2",
    "link_thumb": "https://live.staticflickr.com/65535/51686489600_0af162edc2_o.gif",
    "id_album": "389318914",
    "total": 26,
    "size_max_detail_page": 1,
    "list_detail": [
      {
        "index_page": 0,
        "link_page": "https://github.com/lmbstudiocontact/mb4_dt_alb_0/raw/main/14132021_dta_389318914_index_0.json"
      }
    ]
  },
  {
    "title": "Naruto Anime_L1",
    "link_thumb": "https://live.staticflickr.com/65535/51682806269_2914727852_o.gif",
    "id_album": "1894397983",
    "total": 37,
    "size_max_detail_page": 1,
    "list_detail": [
      {
        "index_page": 0,
        "link_page": "https://github.com/lmbstudiocontact/mb4_dt_alb_0/raw/main/14132021_dta_1894397983_index_0.json"
      }
    ]
  },
  {
    "title": "Minions Cartoon",
    "link_thumb": "https://live.staticflickr.com/65535/51670975507_e1cfcdb85e_o.gif",
    "id_album": "-251636533",
    "total": 5,
    "size_max_detail_page": 1,
    "list_detail": [
      {
        "index_page": 0,
        "link_page": "https://github.com/lmbstudiocontact/mb4_dt_alb_0/raw/main/14132021_dta_-251636533_index_0.json"
      }
    ]
  },
  {
    "title": "Panda Art_L4",
    "link_thumb": "https://live.staticflickr.com/65535/51685772831_2a96ea30b9_o.gif",
    "id_album": "586574346",
    "total": 5,
    "size_max_detail_page": 1,
    "list_detail": [
      {
        "index_page": 0,
        "link_page": "https://github.com/lmbstudiocontact/mb4_dt_alb_0/raw/main/14132021_dta_586574346_index_0.json"
      }
    ]
  },
  {
    "title": "Raccoons_L1",
    "link_thumb": "https://live.staticflickr.com/65535/51688222584_95c7603c96_o.gif",
    "id_album": "1998705264",
    "total": 20,
    "size_max_detail_page": 1,
    "list_detail": [
      {
        "index_page": 0,
        "link_page": "https://github.com/lmbstudiocontact/mb4_dt_alb_0/raw/main/14132021_dta_1998705264_index_0.json"
      }
    ]
  },
  {
    "title": "Donald Duck Cartoon_L10",
    "link_thumb": "https://live.staticflickr.com/65535/51674721632_db349c293a_o.gif",
    "id_album": "683276157",
    "total": 4,
    "size_max_detail_page": 1,
    "list_detail": [
      {
        "index_page": 0,
        "link_page": "https://github.com/lmbstudiocontact/mb4_dt_alb_0/raw/main/14132021_dta_683276157_index_0.json"
      }
    ]
  },
  {
    "title": "Sonic Cartoon",
    "link_thumb": "https://live.staticflickr.com/65535/51671533723_d836f23224_o.gif",
    "id_album": "-1379465926",
    "total": 3,
    "size_max_detail_page": 1,
    "list_detail": [
      {
        "index_page": 0,
        "link_page": "https://github.com/lmbstudiocontact/mb4_dt_alb_0/raw/main/14132021_dta_-1379465926_index_0.json"
      }
    ]
  },
  {
    "title": "Angry Birds_L1",
    "link_thumb": "https://live.staticflickr.com/65535/51673421930_4a85294799_o.gif",
    "id_album": "2112729289",
    "total": 26,
    "size_max_detail_page": 1,
    "list_detail": [
      {
        "index_page": 0,
        "link_page": "https://github.com/lmbstudiocontact/mb4_dt_alb_0/raw/main/14132021_dta_2112729289_index_0.json"
      }
    ]
  }
]